Metadata-Version: 1.0
Name: reacttable
Version: 0.0.1
Summary: I again try to create a dash wrapper for the react table
Home-page: UNKNOWN
Author: Abhinava abhinava1206@gmail.com
Author-email: UNKNOWN
License: MIT
Platform: UNKNOWN
